{
    "tautulli.Activity": "活动",
    "tautulli.Audio": "音频",
    "tautulli.BackingUpConfiguration": "正在备份配置…",
    "tautulli.BackingUpConfigurationDescription": "在后台备份您的配置",
    "tautulli.BackingUpConfigurationFailed": "备份配置失败",
    "tautulli.BackingUpDatabase": "正在备份数据库…",
    "tautulli.BackingUpDatabaseDescription": "在后台备份您的数据库",
    "tautulli.BackingUpDatabaseFailed": "备份数据库失败",
    "tautulli.BackupConfiguration": "备份配置",
    "tautulli.BackupDatabase": "备份数据库",
    "tautulli.Bandwidth": "带宽",
    "tautulli.Burn": "燃烧",
    "tautulli.Container": "容器",
    "tautulli.Copy": "复制",
    "tautulli.DeleteCache": "删除缓存",
    "tautulli.DeleteImageCache": "删除图像缓存",
    "tautulli.DeleteTemporarySessions": "删除临时会话",
    "tautulli.DeletingCache": "正在删除缓存…",
    "tautulli.DeletingCacheDescription": "正在删除 Tautulli 缓存",
    "tautulli.DeletingCacheFailed": "删除缓存失败",
    "tautulli.DeletingImageCacheDescription": "正在删除 Tautulli 图片缓存",
    "tautulli.ActivityDetails": "活动详情",
    "tautulli.DeletingImageCacheFailed": "删除图片缓存失败",
    "tautulli.DeletingTemporarySessionsDescription": "正在删除临时会话",
    "tautulli.DeletingTemporarySessionsFailed": "删除临时会话失败",
    "tautulli.DirectPlay": "直接播放",
    "tautulli.DirectPlays": "直接播放",
    "tautulli.DirectStream": "直播",
    "tautulli.DirectStreams": "直接流",
    "tautulli.Duration": "持续时间",
    "tautulli.Episode": "剧集{}",
    "tautulli.ETA": "预计到达时间",
    "tautulli.History": "历史",
    "tautulli.Library": "图书馆",
    "tautulli.Location": "定位",
    "tautulli.Metadata": "元数据",
    "tautulli.More": "更多",
    "tautulli.None": "没有",
    "tautulli.Platform": "平台",
    "tautulli.Player": "播放器",
    "tautulli.Product": "产品",
    "tautulli.Quality": "画质",
    "tautulli.SessionEnded": "会话结束",
    "tautulli.Sessions": "会话",
    "tautulli.SessionsOne": "1 节",
    "tautulli.SessionsMany": "{} 会话",
    "tautulli.Stream": "流",
    "tautulli.Terminate": "终止",
    "tautulli.TerminationAttachMessage": "您可以选择在下方附加终止消息。",
    "tautulli.TerminationConfirmMessage": "您要终止此会话吗？",
    "tautulli.TerminationMessage": "终止消息",
    "tautulli.TerminatedSession": "终止的会话",
    "tautulli.TerminateSession": "终止会话",
    "tautulli.Throttled": "节流",
    "tautulli.Title": "标题",
    "tautulli.Transcode": "转码",
    "tautulli.Transcodes": "转码",
    "tautulli.User": "用户",
    "tautulli.Users": "使用者",
    "tautulli.Video": "视频",
    "tautulli.ViewWebGUI": "网页图形用户界面",
    "tautulli.Year": "年",
    "tautulli.Subtitle": "副标题",
    "tautulli.DeletingImageCache": "正在删除图像缓存…",
    "tautulli.DeletingTemporarySessions": "正在删除临时会话…",
    "tautulli.NoActiveStreams": "没有活动流",
    "tautulli.Season": "季 {}",
    "tautulli.TerminateSessionFailed": "终止会话失败",
    "tautulli.Converting": "转换",
    "tautulli.Speed": "倍速:{}x",
    "tautulli.ActivityRefreshRate": "活动刷新率",
    "tautulli.LibraryDetails": "库详细信息",
    "tautulli.DefaultTerminationMessage": "默认终止消息",
    "tautulli.Graphs": "曲线图",
    "tautulli.MediaDetails": "媒体详细信息",
    "tautulli.Statistics": "统计数据",
    "tautulli.StatisticsItemCount": "统计项目计数"
}
